videl/__init__.py
videl-0.0.2.dist-info/licenses/LICENSE
videl-0.0.2.dist-info/METADATA
videl-0.0.2.dist-info/WHEEL
videl-0.0.2.dist-info/top_level.txt
videl-0.0.2.dist-info/RECORD
