Metadata-Version: 2.4
Name: videl
Version: 0.0.2
Summary: A research-driven computer vision and deep learning python library build on top of pytorch, covering various vision tasks and focusing on small models.
Author-email: Christos Kyrkou <ckyrkou@gmail.com>
License: Attribution-NonCommercial-ShareAlike 4.0 International
Project-URL: Homepage, https://https://github.com/ckyrkou/videl
Keywords: computer-vision,edge-ai,uav,deep-learning,efficient models,small models,perception
Classifier: Programming Language :: Python :: 3
Classifier: License :: Free for non-commercial use
Classifier: Operating System :: OS Independent
Classifier: Topic :: Scientific/Engineering :: Artificial Intelligence
Requires-Python: >=3.12
License-File: LICENSE
Dynamic: license-file
